ipdatacloud/__init__.py
ipdatacloud/ip.py
ipdatacloud-1.0.3.dist-info/LICENSE
ipdatacloud-1.0.3.dist-info/METADATA
ipdatacloud-1.0.3.dist-info/WHEEL
ipdatacloud-1.0.3.dist-info/top_level.txt
ipdatacloud-1.0.3.dist-info/RECORD
