Metadata-Version: 2.1
Name: ipdatacloud
Version: 1.0.3
Summary: IPv4 Destination Query
Home-page: https://gitee.com/ipdatacloud_admin/ipdatacloud/blob/main/ipv4/python
Author: lj-hfy
Author-email: 2338001356@qq.com
Classifier: Programming Language :: Python :: 3
Classifier: License :: OSI Approved :: MIT License
Classifier: Operating System :: OS Independent
Requires-Python: >=3.6
License-File: LICENSE
